agent/__init__.py
agent/consts.py
agent/exc.py
agent/serve.py
agent/api/__init__.py
agent/api/client.py
agent/api/grand.py
agent/api/jira.py
agent/api/qualityplatform.py
agent/manager/__init__.py
agent/server/__init__.py
agent/server/api.py
agent/util/__init__.py
agent/util/tools.py
agent/worker/__init__.py
agent/worker/base.py
agent/worker/monkey.py
tests/__init__.py
tests/grand_test.py
tests/jira_test.py
tests/tools_test.py
qpagent-820.dist-info/LICENSE
qpagent-820.dist-info/METADATA
qpagent-820.dist-info/WHEEL
qpagent-820.dist-info/entry_points.txt
qpagent-820.dist-info/top_level.txt
qpagent-820.dist-info/zip-safe
qpagent-820.dist-info/RECORD
