Metadata-Version: 2.1
Name: qpagent
Version: 820
Summary: agent
Home-page: https://git.elenet.me/waimaiqa/qualityplatform.agent.git
Author: mafei
Author-email: fei.ma03@ele.me
License: MIT Licence
Platform: any
Requires-Dist: requests
Requires-Dist: bottle
Requires-Dist: click
Requires-Dist: shutit
Requires-Dist: enum34
Requires-Dist: apptoolkit
Requires-Dist: python-jenkins
